acrv_datasets/__init__.py
acrv_datasets/__main__.py
acrv_datasets/acrv_datasets.py
acrv_datasets/datasets.yaml
acrv_datasets/downloader.py
acrv_datasets-0.9.3.dist-info/LICENSE.txt
acrv_datasets-0.9.3.dist-info/METADATA
acrv_datasets-0.9.3.dist-info/WHEEL
acrv_datasets-0.9.3.dist-info/top_level.txt
acrv_datasets-0.9.3.dist-info/RECORD
