Metadata-Version: 2.1
Name: acrv-datasets
Version: 0.9.3
Summary: Datasets manager for the Best of ACRV
Home-page: https://github.com/best-of-acrv/acrv-datasets
Author: Ben Talbot
Author-email: b.talbot@qut.edu.au
License: UNKNOWN
Platform: UNKNOWN
Classifier: Development Status :: 4 - Beta
Classifier: Programming Language :: Python :: 3
Classifier: License :: OSI Approved :: BSD License
Classifier: Operating System :: OS Independent
License-File: LICENSE.txt
Requires-Dist: colorama
Requires-Dist: pyyaml
Requires-Dist: requests
Requires-Dist: tqdm
